cword/__init__.py
cword/__main__.py
cword/cli.py
cword-0.1.0.dist-info/METADATA
cword-0.1.0.dist-info/WHEEL
cword-0.1.0.dist-info/entry_points.txt
cword-0.1.0.dist-info/licenses/LICENSE
cword-0.1.0.dist-info/RECORD
