Metadata-Version: 2.4
Name: cword
Version: 0.1.0
Summary: A CLI spelling assistant powered by AI
Project-URL: Homepage, https://github.com/baraa404/Terminal-Spelling-Assistant
Project-URL: Repository, https://github.com/baraa404/Terminal-Spelling-Assistant
Project-URL: Issues, https://github.com/baraa404/Terminal-Spelling-Assistant/issues
Project-URL: Documentation, https://github.com/baraa404/Terminal-Spelling-Assistant#readme
Author-email: Baraa <baraa0email@gmail.com>
Maintainer-email: Baraa <baraa0email@gmail.com>
License-Expression: MIT
License-File: LICENSE
Keywords: ai,assistant,cli,correction,gemini,grammar,spelling,text-processing
Classifier: Development Status :: 4 - Beta
Classifier: Environment :: Console
Classifier: Intended Audience :: End Users/Desktop
Classifier: License :: OSI Approved :: MIT License
Classifier: Operating System :: OS Independent
Classifier: Programming Language :: Python :: 3
Classifier: Programming Language :: Python :: 3.7
Classifier: Programming Language :: Python :: 3.8
Classifier: Programming Language :: Python :: 3.9
Classifier: Programming Language :: Python :: 3.10
Classifier: Programming Language :: Python :: 3.11
Classifier: Programming Language :: Python :: 3.12
Classifier: Topic :: Text Processing :: Linguistic
Classifier: Topic :: Utilities
Requires-Python: >=3.7
Requires-Dist: requests>=2.25.0
